fosqca/__init__.py
fosqca/__main__.py
fosqca/fosqca.py
fosQCA-0.5.0.dist-info/LICENSE
fosQCA-0.5.0.dist-info/METADATA
fosQCA-0.5.0.dist-info/WHEEL
fosQCA-0.5.0.dist-info/entry_points.txt
fosQCA-0.5.0.dist-info/top_level.txt
fosQCA-0.5.0.dist-info/RECORD
