Metadata-Version: 2.1
Name: fosQCA
Version: 0.5.0
Summary: A QCA tool that can optimise solutions for multiple input sets
Home-page: https://github.com/Tibo-Ulens/fosQCA
Author: Tibo Ulens
Author-email: ulens.tibo@gmail.com
License: MIT
Platform: all
Requires-Python: >=3.12
License-File: LICENSE
Requires-Dist: pandas
